colour_datasets/__init__.py
colour_datasets/examples/examples_load.py
colour_datasets/loaders/__init__.py
colour_datasets/loaders/abstract.py
colour_datasets/loaders/asano2015.py
colour_datasets/loaders/brendel2020.py
colour_datasets/loaders/dyer2017.py
colour_datasets/loaders/ebner1998.py
colour_datasets/loaders/hung1995.py
colour_datasets/loaders/jakob2019.py
colour_datasets/loaders/jiang2013.py
colour_datasets/loaders/karge2015.py
colour_datasets/loaders/kuopio.py
colour_datasets/loaders/labsphere2019.py
colour_datasets/loaders/luo1997.py
colour_datasets/loaders/luo1999.py
colour_datasets/loaders/solomotav2023.py
colour_datasets/loaders/winquist2022.py
colour_datasets/loaders/xrite2016.py
colour_datasets/loaders/zhao2009.py
colour_datasets/loaders/tests/__init__.py
colour_datasets/loaders/tests/test_abstract.py
colour_datasets/loaders/tests/test_asano2015.py
colour_datasets/loaders/tests/test_brendel2020.py
colour_datasets/loaders/tests/test_dyer2017.py
colour_datasets/loaders/tests/test_ebner1998.py
colour_datasets/loaders/tests/test_hung1995.py
colour_datasets/loaders/tests/test_jakob2019.py
colour_datasets/loaders/tests/test_jiang2013.py
colour_datasets/loaders/tests/test_karge2015.py
colour_datasets/loaders/tests/test_kuopio.py
colour_datasets/loaders/tests/test_labsphere2019.py
colour_datasets/loaders/tests/test_luo1997.py
colour_datasets/loaders/tests/test_luo1999.py
colour_datasets/loaders/tests/test_solomotav2023.py
colour_datasets/loaders/tests/test_winquist2022.py
colour_datasets/loaders/tests/test_xrite2016.py
colour_datasets/loaders/tests/test_zhao2009.py
colour_datasets/loaders/tests/resources/Kuopio_Typical.mat
colour_datasets/records/__init__.py
colour_datasets/records/configuration.py
colour_datasets/records/zenodo.py
colour_datasets/records/tests/__init__.py
colour_datasets/records/tests/test_configuration.py
colour_datasets/records/tests/test_zenodo.py
colour_datasets/utilities/__init__.py
colour_datasets/utilities/common.py
colour_datasets-0.2.7.dist-info/METADATA
colour_datasets-0.2.7.dist-info/WHEEL
colour_datasets-0.2.7.dist-info/licenses/LICENSE
colour_datasets-0.2.7.dist-info/RECORD
